13_Final_Practice_Projects/116_Memory_Controller_Basic/design.v
module single_port_ram(
    input [7:0] d_in,
    input [4:0] ram_addr,
    input w_en,
    input clk,
    output reg [7:0] d_out
);
  
  reg [7:0] ram_mem [31:0];
  
  always @(posedge clk) begin
    if (w_en) begin
      ram_mem[ram_addr] <= d_in;
    end
    d_out <= ram_mem[ram_addr]; 
  end
  
endmodule

module mem_controller(input clk,
                      input rst,
                      
                      //Processor to Controller
                      input start,
                      input write,
                      input [4:0] address,
                      input [7:0] data,
                      output reg [7:0] d_out,
                      output reg ready,
                      
                      //Controller to ram
                      output [7:0] ram_data_in,
                      output w_en,
                      output [4:0] ram_addr,
                      input [7:0] ram_data_out
                     );
  
  
  reg state, nxt_state;
  localparam IDLE=0,WAIT=1;
  
  assign ram_addr = address;
  assign ram_data_in = data;
  assign w_en = start && write && (state==IDLE);
  
  always@(posedge clk) begin
    if(rst)
      state<=IDLE;
    else
      state<=nxt_state;
  end
  
  always@(*) begin
    nxt_state=state;
    case(state)
        IDLE: begin
          if(start) begin
            if(write)
              nxt_state=IDLE;
            else
              nxt_state= WAIT;
          end
        end
        WAIT: nxt_state=IDLE;
        default: nxt_state=IDLE;
      endcase
  end
  
  
  always@(posedge clk) begin
    if(rst) begin
      ready<=0;
      d_out<=0;
    end
    else begin
      case(state)
        IDLE: begin
          ready<=0;
          if(start) begin
            if(write) begin
              ready<=1;
            end
          end
        end
        WAIT: begin
          d_out<=ram_data_out;
          ready<=1'b1;
        end
        default: begin
          ready<=0;
          d_out<=0;
        end
      endcase
    end
  end
  
endmodule

13_Final_Practice_Projects/116_Memory_Controller_Basic/design_tb.v
module mem_system_tb();
  reg clk;
  reg rst;
  reg start;
  reg write;
  reg [4:0] address;
  reg [7:0] data;
  wire [7:0] d_out;
  wire ready;
  
  wire [7:0] ram_data_in;
  wire       w_en;
  wire [4:0] ram_addr;
  wire [7:0] ram_data_out;

  
  mem_controller U_CONTROLLER (
    .clk(clk), .rst(rst),
    .start(start), .write(write), .address(address), .data(data),
    .d_out(d_out), .ready(ready),
    .ram_data_in(ram_data_in), .w_en(w_en), .ram_addr(ram_addr), .ram_data_out(ram_data_out)
  );
  
  single_port_ram U_RAM (
    .clk(clk),
    .d_in(ram_data_in),
    .ram_addr(ram_addr),
    .w_en(w_en),
    .d_out(ram_data_out)
  );
  
  always #10 clk = ~clk;
  
  initial begin
    $dumpfile("image.vcd");
    $dumpvars(0, mem_system_tb);
    
    
    clk     = 0;
    rst     = 1;
    start   = 0;
    write   = 0;
    address = 0;
    data    = 0;
    
     
    #25;
    rst = 0;
    @(posedge clk);
        
    //write
    $display("WRITE: Addr=5, Data=0xA5");
    address = 5;
    data    = 8'hA5;
    write   = 1;
    start   = 1;
    
    @(posedge clk);
    start   = 0; 
    write   = 0;
    
    
    while(!ready) @(posedge clk);
    $display("Write acknowledged! Ready : %b\n", ready);
    
    
    @(posedge clk);
    
    //read
    $display("Read: Addr=5");
    address = 5;
    write   = 0;
    start   = 1;
    
    
    @(posedge clk); 
    start   = 0; 
   
    while(!ready) @(posedge clk);
    
    #1;
    $display("Read complete! Ready=%b | Data Read out: 0x%h", ready, d_out);
    
    if (d_out == 8'hA5)
      $display("\n*** Pass: Read data matches written ***");
    else
      $display("\n*** Fail: Data Mismatch! Expected 0xA5, got 0x%h ***", d_out);
      
    #40;
    $finish();
  end

endmodule

13_Final_Practice_Projects/116_Memory_Controller_Basic/image.vcd
$date
	Thu Jul 16 04:51:36 2026
$end
$version
	Icarus Verilog
$end
$timescale
	1s
$end
$scope module mem_system_tb $end
$var wire 1 ! w_en $end
$var wire 1 " ready $end
$var wire 8 # ram_data_out [7:0] $end
$var wire 8 $ ram_data_in [7:0] $end
$var wire 5 % ram_addr [4:0] $end
$var wire 8 & d_out [7:0] $end
$var reg 5 ' address [4:0] $end
$var reg 1 ( clk $end
$var reg 8 ) data [7:0] $end
$var reg 1 * rst $end
$var reg 1 + start $end
$var reg 1 , write $end
$scope module U_CONTROLLER $end
$var wire 5 - address [4:0] $end
$var wire 1 ( clk $end
$var wire 8 . data [7:0] $end
$var wire 5 / ram_addr [4:0] $end
$var wire 8 0 ram_data_in [7:0] $end
$var wire 1 * rst $end
$var wire 1 + start $end
$var wire 1 ! w_en $end
$var wire 1 , write $end
$var wire 8 1 ram_data_out [7:0] $end
$var parameter 32 2 IDLE $end
$var parameter 32 3 WAIT $end
$var reg 8 4 d_out [7:0] $end
$var reg 1 5 nxt_state $end
$var reg 1 " ready $end
$var reg 1 6 state $end
$upscope $end
$scope module U_RAM $end
$var wire 1 ( clk $end
$var wire 8 7 d_in [7:0] $end
$var wire 5 8 ram_addr [4:0] $end
$var wire 1 ! w_en $end
$var reg 8 9 d_out [7:0] $end
$upscope $end
$upscope $end
$enddefinitions $end
$comment Show the parameter values. $end
$dumpall
b1 3
b0 2
$end
#0
$dumpvars
bx 9
b0 8
b0 7
x6
05
bx 4
bx 1
b0 0
b0 /
b0 .
b0 -
0,
0+
1*
b0 )
0(
b0 '
bx &
b0 %
b0 $
bx #
x"
0!
$end
#10
06
b0 &
b0 4
0"
1(
#20
0(
#25
0*
#30
1"
1!
1+
1,
b10100101 $
b10100101 0
b10100101 7
b10100101 )
b10100101 .
b101 %
b101 /
b101 8
b101 '
b101 -
1(
#40
0(
#50
1"
0!
0,
0+
1(
#60
0(
#70
b10100101 #
b10100101 1
b10100101 9
0"
15
1+
1(
#80
0(
#90
16
05
0+
1(
#100
0(
#110
1"
b10100101 &
b10100101 4
06
1(
#120
0(
#130
0"
1(
