02_Basic_Combinational/010_Half_Subtractor/design.v
module half_sub(input x,
                  input y,
                  output bout,
                  output diff);
  
  wire not_x;
  
  not(not_x,x);
  
  xor(diff,x,y);
  and(bout,not_x,y);
  
endmodule

02_Basic_Combinational/011_Full_Subtractor/design.v
`include "../010_Half_Subtractor/design.v"
module full_sub(input x,
                input y,
                input bin,
                output diff,
                output bout);

  wire d1,bout1,bout2;

  half_sub sub_1(.x(x),
                 .y(y),
                 .bout(bout1),
                 .diff(d1));
  half_sub sub_2(.x(d1),
                 .y(bin),
                 .bout(bout2),
                 .diff(diff));

  or(bout,bout1,bout2);

endmodule

02_Basic_Combinational/011_Full_Subtractor/design_tb.v
module full_sub_tb();
  reg x,y,bin;
  wire bout, diff;
  
  full_sub fa(.x(x),
              .y(y),
              .bin(bin),
              .bout(bout),
              .diff(diff)
               );
  
  initial begin
    #10 x = 0; y = 0; bin = 0;
    $dumpfile("image.vcd");
    $dumpvars(0);
    $monitor("x = %b, y = %b, bin = %b, diff = %b, bout = %b",x,y,bin,diff,bout);
    #10 x = 0; y = 0; bin = 1;
    #10 x = 0; y = 1; bin = 0;
    #10 x = 0; y = 1; bin = 1;
    #10 x = 1; y = 0; bin = 0;
    #10 x = 1; y = 0; bin = 1;
    #10 x = 1; y = 1; bin = 0;
    #10 x = 1; y = 1; bin = 1;
    #10 $finish();
  end
  
endmodule

02_Basic_Combinational/011_Full_Subtractor/image.vcd
$date
	Thu Jun  4 02:03:43 2026
$end
$version
	Icarus Verilog
$end
$timescale
	1s
$end
$scope module full_sub_tb $end
$var wire 1 ! diff $end
$var wire 1 " bout $end
$var reg 1 # bin $end
$var reg 1 $ x $end
$var reg 1 % y $end
$scope module fa $end
$var wire 1 # bin $end
$var wire 1 " bout $end
$var wire 1 $ x $end
$var wire 1 % y $end
$var wire 1 ! diff $end
$var wire 1 & d1 $end
$var wire 1 ' bout2 $end
$var wire 1 ( bout1 $end
$scope module sub_1 $end
$var wire 1 ( bout $end
$var wire 1 & diff $end
$var wire 1 ) not_x $end
$var wire 1 $ x $end
$var wire 1 % y $end
$upscope $end
$scope module sub_2 $end
$var wire 1 ' bout $end
$var wire 1 ! diff $end
$var wire 1 * not_x $end
$var wire 1 & x $end
$var wire 1 # y $end
$upscope $end
$upscope $end
$upscope $end
$enddefinitions $end
$comment Show the parameter values. $end
$dumpall
$end
#10
$dumpvars
1*
1)
0(
0'
0&
0%
0$
0#
0"
0!
$end
#20
1"
1!
1'
1#
#30
0*
0'
1&
1(
0#
1%
#40
0!
1#
#50
0"
1!
0(
0)
0#
0%
1$
#60
0!
1#
#70
1*
0&
0#
1%
#80
1"
1!
1'
1#
