02_Basic_Combinational/009_Full_Adder/design.v
module half_adder(input a,
                  input b,
                  output cout,
                  output sum);
  
  xor(sum,a,b);
  and(cout,a,b);
  
endmodule

module full_adder(input a,
                  input b,
                  input cin,
                  output sum,
                  output cout);

  wire sum1,cout1,cout2;

  half_adder ha_1(.a(a),
                  .b(b),
                  .cout(cout1),
                  .sum(sum1));
  half_adder ha_2(.a(sum1),
                  .b(cin),
                  .cout(cout2),
                  .sum(sum));

  or(cout,cout1,cout2);

endmodule

02_Basic_Combinational/009_Full_Adder/design_tb.v
module full_adder_tb();
  reg a,b,cin;
  wire cout, sum;
  
  full_adder fa(.a(a),
                .b(b),
                .cin(cin),
                .cout(cout),
                .sum(sum)
               );
  
  initial begin
    #10 a = 0; b = 0; cin = 0;
    $dumpfile("image.vcd");
    $dumpvars(0);
    $monitor("a = %b, b = %b, cin = %b, sum = %b, cout = %b",a,b,cin,sum,cout);
    #10 a = 0; b = 0; cin = 1;
    #10 a = 0; b = 1; cin = 0;
    #10 a = 0; b = 1; cin = 1;
    #10 a = 1; b = 0; cin = 0;
    #10 a = 1; b = 0; cin = 1;
    #10 a = 1; b = 1; cin = 0;
    #10 a = 1; b = 1; cin = 1;
    #10 $finish();
  end
  
endmodule

02_Basic_Combinational/009_Full_Adder/image.vcd
$date
	Thu Jun  4 02:00:01 2026
$end
$version
	Icarus Verilog
$end
$timescale
	1s
$end
$scope module full_adder_tb $end
$var wire 1 ! sum $end
$var wire 1 " cout $end
$var reg 1 # a $end
$var reg 1 $ b $end
$var reg 1 % cin $end
$scope module fa $end
$var wire 1 # a $end
$var wire 1 $ b $end
$var wire 1 % cin $end
$var wire 1 " cout $end
$var wire 1 & sum1 $end
$var wire 1 ! sum $end
$var wire 1 ' cout2 $end
$var wire 1 ( cout1 $end
$scope module ha_1 $end
$var wire 1 # a $end
$var wire 1 $ b $end
$var wire 1 ( cout $end
$var wire 1 & sum $end
$upscope $end
$scope module ha_2 $end
$var wire 1 & a $end
$var wire 1 % b $end
$var wire 1 ' cout $end
$var wire 1 ! sum $end
$upscope $end
$upscope $end
$upscope $end
$enddefinitions $end
$comment Show the parameter values. $end
$dumpall
$end
#10
$dumpvars
0(
0'
0&
0%
0$
0#
0"
0!
$end
#20
1!
1%
#30
1&
0%
1$
#40
1"
0!
1'
1%
#50
0"
1!
0'
0%
0$
1#
#60
1"
0!
1'
1%
#70
0'
0&
1(
0%
1$
#80
1!
1%
