09_Memory_Basics/079_Single_Port_RAM/design.v
module single_port_ram(input [7:0] d_in,
                       input [4:0] ram_addr,
                       input w_en,
                       input clk,
                       input rst,
                       output [7:0] d_out
                      );
  
  reg [7:0] ram_mem [31:0];
  reg [4:0] addr_reg;
  
  always @(posedge clk or posedge rst) begin
    if(rst) begin
      for(integer i=0;i<32;i=i+1)
        ram_mem[i]<=0;
      addr_reg<=0;
    end
    else begin
      if(w_en)
        ram_mem[ram_addr] <= d_in;
      else 
        addr_reg <= ram_addr;
    end
  end
  
  assign d_out = ram_mem[addr_reg];
  
endmodule

09_Memory_Basics/079_Single_Port_RAM/design_tb.v
module single_port_ram_tb();
  reg [7:0] d_in;
  reg [4:0] ram_addr;
  reg w_en,clk,rst;
  wire [7:0]d_out;
  
  single_port_ram DUT(.d_in(d_in),
                      .ram_addr(ram_addr),
                      .w_en(w_en),
                      .clk(clk),
                      .rst(rst),
                      .d_out(d_out)
                     );
  
  reg [4:0] addr_r;
  reg [7:0] data_r;
  
  always #10 clk = ~clk;
  
  //task for read op and write op in tb
  task write;
    input [4:0] addr;
    input [7:0] data;
    begin
      ram_addr = addr;
      d_in = data;
      w_en = 1;
      @(posedge clk);
      #1
      w_en = 0;
      $display("data = %b, memory stored = %b",d_in,ram_addr);
    end
  endtask
      
  
  task read;
    input [4:0] addr;
    begin
      ram_addr = addr;
      w_en = 0;
      @(posedge clk);
      $display("address = %b, Read data = %b",ram_addr,d_out);
    end
  endtask
  
  initial begin
    $dumpfile("image.vcd");
    $dumpvars(0,single_port_ram_tb.DUT);
    clk = 0;
    rst = 1;
    @(posedge clk); 
    rst = 0;
    // Write random data to random addresses
    repeat (20) begin
      addr_r = $urandom_range(0, 31);
      data_r = $urandom_range(0, 255);
      write(addr_r, data_r);
    end

    // Read back from random addresses
    repeat (10) begin
      addr_r = $urandom_range(0, 31);
      read(addr_r);
    end
    
    @(posedge clk);
    $finish();
  end
endmodule

09_Memory_Basics/079_Single_Port_RAM/image.vcd
$date
	Sat Jun 13 02:29:02 2026
$end
$version
	Icarus Verilog
$end
$timescale
	1s
$end
$scope module single_port_ram_tb $end
$scope module DUT $end
$var wire 1 ! clk $end
$var wire 8 " d_in [7:0] $end
$var wire 8 # d_out [7:0] $end
$var wire 5 $ ram_addr [4:0] $end
$var wire 1 % rst $end
$var wire 1 & w_en $end
$var reg 5 ' addr_reg [4:0] $end
$scope begin $ivl_for_loop0 $end
$var integer 32 ( i [31:0] $end
$upscope $end
$upscope $end
$upscope $end
$enddefinitions $end
$comment Show the parameter values. $end
$dumpall
$end
#0
$dumpvars
b100000 (
b0 '
x&
1%
bx $
b0 #
bx "
0!
$end
#10
1&
b1000000 "
b10010 $
0%
1!
#20
0!
#30
1!
#31
b110001 "
b0 $
1&
#40
0!
#50
b110001 #
1!
#51
b11000110 "
b10000 $
1&
#60
0!
#70
1!
#71
b1001 "
b110 $
1&
#80
0!
#90
1!
#91
b10000110 "
b10000 $
1&
#100
0!
#110
1!
#111
b10011110 "
b10111 $
1&
#120
0!
#130
1!
#131
b11000110 "
b11110 $
1&
#140
0!
#150
1!
#151
b1100011 "
b11111 $
1&
#160
0!
#170
1!
#171
b1010101 "
b1100 $
1&
#180
0!
#190
1!
#191
b111011 "
b11110 $
1&
#200
0!
#210
1!
#211
b11000111 "
b1 $
1&
#220
0!
#230
1!
#231
b1100111 "
b11111 $
1&
#240
0!
#250
1!
#251
b1100010 "
b1110 $
1&
#260
0!
#270
1!
#271
b1011110 "
b10101 $
1&
#280
0!
#290
1!
#291
b110010 "
b10 $
1&
#300
0!
#310
1!
#311
b10000101 "
b110 $
1&
#320
0!
#330
1!
#331
b10010000 "
b1000 $
1&
#340
0!
#350
1!
#351
b1001110 "
b11010 $
1&
#360
0!
#370
1!
#371
b1001 "
b1001 $
1&
#380
0!
#390
1!
#391
b101001 "
b0 $
1&
#400
0!
#410
b101001 #
1!
#411
b10110 $
0&
#420
0!
#430
b0 #
b1101 '
b1101 $
1!
#440
0!
#450
b101001 #
b0 '
b0 $
1!
#460
0!
#470
b0 #
b1010 '
b1010 $
1!
#480
0!
#490
b10001 '
b10001 $
1!
#500
0!
#510
b1010101 #
b1100 '
b1100 $
1!
#520
0!
#530
b1000000 #
b10010 '
b10010 $
1!
#540
0!
#550
b10000110 #
b10000 '
b10000 $
1!
#560
0!
#570
b1010101 #
b1100 '
b1100 $
1!
#580
0!
#590
b0 #
b11 '
b11 $
1!
