08_Finite_State_Machines/073_Traffic_Light_Controller/design.v
module traffic_light(input clk,
                      input reset,
                      input E, //east side traffic sensor
                      input E_R, //east side right turn lane sensor
                      input pri_E, //priority vehicle east
                      input W,
                      input W_R,
                      input pri_W, 
                      input N,
                      input N_R,
                      input pri_N, 
                      input S,
                      input S_R,
                      input pri_S, 
                      output reg [3:1] light_E, //[1] index is greeen, [2] yellow, [3] red
                      output reg ped_light_EW, //pedestrian light East and West,1 green,0 red
                      output reg light_E_R, //right turn light east 1 green, 0 red
                      output reg [3:1] light_W,
                      output reg light_W_R,
                      output reg [3:1] light_N,
                      output reg ped_light_NS,
                      output reg light_N_R,
                      output reg [3:1] light_S,
                      output reg light_S_R
                     );
  
  reg [2:0] state,nxt_state;
  localparam EAST=0,EAST_R=1,WEST=2,WEST_R=3,NORTH=4,NORTH_R=5,
  			 SOUTH=6,SOUTH_R=7;
  
  always@(posedge clk) begin
    if(reset)
      state<=EAST;
    else
      state<=nxt_state;
  end
  
  reg [3:0] count;
  reg c,r,pri;
  
  
  
  always@(posedge clk) begin
    if(reset)
      count<=0;
    else begin
      count<=count+1;
      if(r)
        count<=0;
    end
  end
    
  
  always@(*) begin
    nxt_state = state;
    r=0;
    pri=0;
    case(state)
      
      EAST: begin
        if(pri_E) begin
          r=1;
          nxt_state = EAST_R;
        end
        else if(pri_W) begin
          r=1;
          nxt_state = WEST_R;
        end
        else if(pri_N) begin
          r=1;
          nxt_state = NORTH_R;
        end
        else if(pri_S) begin
          r=1;
          nxt_state = SOUTH_R;
        end
        else begin
          if(!E &!E_R && count<7) begin
            if(S)
              nxt_state = SOUTH;
            else if(S_R)
              nxt_state = SOUTH_R;
            else if(W)
              nxt_state = WEST;
            else if(W_R)
              nxt_state = WEST_R;
            else if(N)
              nxt_state = NORTH;
            else if(N_R)
              nxt_state = NORTH_R;
            else nxt_state = EAST;
          end
          else if(count==5 && E_R)
            nxt_state=EAST_R;
          else if(count==15) begin
            //$display("loop1");
            nxt_state = SOUTH;
          end
          else begin
            nxt_state = EAST;
          end
        end
      end
      
      
      EAST_R: begin
        if(!pri_E)
          r=0;
        if(pri_W) begin
          pri=1;
          if(count!=15)
            nxt_state=EAST_R;
          else
            nxt_state = WEST_R;
        end
        else if(pri_N) begin
          pri=1;
          if(count!=15)
            nxt_state=EAST_R;
          else
            nxt_state = NORTH_R;
        end
        else if(pri_S) begin
          pri=1;
          if(count!=15)
            nxt_state=EAST_R;
          else
            nxt_state = SOUTH_R;
        end
        else if(count!=15) begin
          if(!E_R) begin
            if(S)
              nxt_state = SOUTH;
            else if(S_R)
              nxt_state = SOUTH_R;
            else if(W)
              nxt_state = WEST;
            else if(W_R)
              nxt_state = WEST_R;
            else if(N)
              nxt_state = NORTH;
            else if(N_R)
              nxt_state = NORTH_R;
          end
          else     
          	nxt_state = EAST_R;
        end
        else nxt_state = SOUTH;
      end
      
      SOUTH: begin
        if(pri_S) begin
          r=1;
          nxt_state = SOUTH_R;
        end
        else if(pri_W) begin
          pri=1;
          if(count!=15)
            nxt_state=EAST;
          else
            nxt_state = WEST_R;
        end
        else if(pri_N) begin
          pri=1;
          if(count!=15)
            nxt_state=EAST;
          else
            nxt_state = NORTH_R;
        end
        else if(pri_E) begin
          
          pri=1;
          if(count!=15)
            nxt_state=SOUTH;
          else
            nxt_state = EAST_R;
        end
        else begin
          if(!E &!E_R && count<7) begin
            if(E)
              nxt_state = EAST;
            else if(E_R)
              nxt_state = EAST_R;
            else if(W)
              nxt_state = WEST;
            else if(W_R)
              nxt_state = WEST_R;
            else if(N)
              nxt_state = NORTH;
            else if(N_R)
              nxt_state = NORTH_R;
            else nxt_state = SOUTH;
          end
          else if(count==7 && S_R)
            nxt_state=SOUTH_R;
          else if(count==15) begin
            //$display("loop2");
            nxt_state = WEST;
          end
          else begin;
            nxt_state = SOUTH;
          end
        end
      end
      
      SOUTH_R: begin
        if(!pri_S)
          r=0;
        if(pri_W) begin
          pri=1;
          if(count!=15)
            nxt_state=EAST_R;
          else
            nxt_state = WEST_R;
        end
        else if(pri_N) begin
          pri=1;
          if(count!=15)
            nxt_state=EAST_R;
          else
            nxt_state = NORTH_R;
        end
        else if(pri_E) begin
          pri=1;
          if(count!=15)
            nxt_state=SOUTH_R;
          else
            nxt_state = EAST_R;
        end
        else if(count!=15) begin
          if(!S_R) begin
            if(W)
              nxt_state = WEST;
            else if(W_R)
              nxt_state = WEST_R;
            else if(N)
              nxt_state = NORTH;
            else if(N_R)
              nxt_state = NORTH_R;
            else if(E)
              nxt_state = EAST;
            else if(E_R)
              nxt_state = EAST_R;
          end
          else     
          	nxt_state = SOUTH_R;
        end
        else nxt_state = WEST;
      end
      
      WEST: begin
        if(pri_W) begin
          r=1;
          nxt_state = WEST_R;
        end
        else if(pri_E) begin
          pri=1;
          if(count!=15)
            nxt_state=WEST;
          else
            nxt_state = EAST_R;
        end
        else if(pri_N) begin
          pri=1;
          if(count!=15)
            nxt_state=WEST;
          else
            nxt_state = NORTH_R;
        end
        else if(pri_S) begin
          pri=1;
          if(count!=15)
            nxt_state=WEST;
          else
            nxt_state = SOUTH_R;
        end
        else begin
          if(!W &!W_R && count<7) begin
            if(S)
              nxt_state = SOUTH;
            else if(S_R)
              nxt_state = SOUTH_R;
            else if(E)
              nxt_state = EAST;
            else if(E_R)
              nxt_state = EAST_R;
            else if(N)
              nxt_state = NORTH;
            else if(N_R)
              nxt_state = NORTH_R;
            else nxt_state = WEST;
          end
          else if(count==5 && W_R)
            nxt_state=W_R;
          else if(count==15) begin
            //$display("loop1");
            nxt_state = NORTH;
          end
          else begin;
            nxt_state = WEST;
          end
        end
      end
      
      WEST_R: begin
        if(!pri_W)
          r=0;
        if(pri_N) begin
          pri=1;
          if(count!=15)
            nxt_state=WEST_R;
          else
            nxt_state = NORTH_R;
        end
        else if(pri_E) begin
          pri=1;
          if(count!=15)
            nxt_state=WEST_R;
          else
            nxt_state = EAST_R;
        end
        else if(pri_S) begin
          pri=1;
          if(count!=15)
            nxt_state=WEST_R;
          else
            nxt_state = SOUTH_R;
        end
        else if(count!=15) begin
          if(!W_R) begin
            if(S)
              nxt_state = SOUTH;
            else if(S_R)
              nxt_state = SOUTH_R;
            else if(E)
              nxt_state = EAST;
            else if(E_R)
              nxt_state = EAST_R;
            else if(N)
              nxt_state = NORTH;
            else if(N_R)
              nxt_state = NORTH_R;
          end
          else     
          	nxt_state = WEST_R;
        end
        else nxt_state = NORTH;
      end
      
      NORTH: begin
        if(pri_N) begin
          r=1;
          nxt_state = NORTH_R;
        end
        else if(pri_W) begin
          pri=1;
          if(count!=15)
            nxt_state=NORTH;
          else
            nxt_state = WEST_R;
        end
        else if(pri_E) begin
          pri=1;
          if(count!=15)
            nxt_state=NORTH;
          else
            nxt_state = EAST_R;
        end
        else if(pri_S) begin
          pri=1;
          if(count!=15)
            nxt_state=NORTH;
          else
            nxt_state = SOUTH_R;
        end
        else begin
          if(!N &!N_R && count<7) begin
            if(S)
              nxt_state = SOUTH;
            else if(S_R)
              nxt_state = SOUTH_R;
            else if(E)
              nxt_state = EAST;
            else if(E_R)
              nxt_state = EAST_R;
            else if(W)
              nxt_state = WEST;
            else if(W_R)
              nxt_state = WEST_R;
            else nxt_state = NORTH;
          end
          else if(count==5 && N_R)
            nxt_state=N_R;
          else if(count==15) begin
            //$display("loop1");
            nxt_state = EAST;
          end
          else begin;
            nxt_state = NORTH;
          end
        end
      end
      
      NORTH_R: begin
        if(!pri_N)
          r=0;
        if(pri_W) begin
          pri=1;
          if(count!=15)
            nxt_state=NORTH_R;
          else
            nxt_state = WEST_R;
        end
        else if(pri_E) begin
          pri=1;
          if(count!=15)
            nxt_state=NORTH_R;
          else
            nxt_state = EAST_R;
        end
        else if(pri_S) begin
          pri=1;
          if(count!=15)
            nxt_state=NORTH_R;
          else
            nxt_state = SOUTH_R;
        end
        else if(count!=15) begin
          if(!N_R) begin
            if(S)
              nxt_state = SOUTH;
            else if(S_R)
              nxt_state = SOUTH_R;
            else if(W)
              nxt_state = WEST;
            else if(W_R)
              nxt_state = WEST_R;
            else if(E)
              nxt_state = EAST;
            else if(E_R)
              nxt_state = EAST_R;
          end
          else     
          	nxt_state = NORTH_R;
        end
        else nxt_state = EAST;
      end
      
      default:nxt_state=state;    
      
    endcase
  end
  
  //output logic
  always@(*) begin
    light_E = 4;
    light_W = 4;
    light_N = 4;
    light_S = 4;
    ped_light_EW = 0;
    case(state)
      EAST: begin
        light_E[1] = 1'b1;
        light_E[3] = 0;
        light_W[1]=1'b1;
        light_W[3] = 0;
        ped_light_EW = 1'b1;
      end
      EAST_R: begin
        light_E[1] = 1'b1;
        light_E[3] = 0;
        light_E_R = 1'b1;
      end
      SOUTH: begin
        light_S[1] = 1'b1;
        light_S[3] = 0;
        light_N[1] = 1'b1;
        light_N[3] = 0;
        ped_light_NS = 1'b1;
      end
      NORTH_R: begin
        light_N[1] = 1'b1;
        light_N[3] = 0;
        light_N_R = 1'b1;
      end
      WEST: begin
        light_W[1] = 1'b1;
        light_W[3] =0;
        light_E[1] = 1'b1;
        light_E[3] = 0;
        ped_light_EW = 1'b1;
      end
      WEST_R: begin
        light_W[1] = 1'b1;
        light_W[3] = 0;
        light_W_R = 1'b1;
      end
      SOUTH: begin
        light_S[1] = 1'b1;
        light_S[3] = 0;
        light_N[1] = 1'b1;
        light_N[3] = 0;
        ped_light_NS = 1'b1;
      end
      SOUTH_R: begin
        light_S[1] = 1'b1;
        light_S[3] = 0;
        light_S_R = 1'b1;
      end
    endcase
  end
  
  
        
  
endmodule

08_Finite_State_Machines/073_Traffic_Light_Controller/tb_design.v
module tb_traffic_light();
  reg clk,reset, E,E_R,pri_E,W,W_R,pri_W,N,N_R,pri_N, 
  			S,S_R,pri_S; 
  
  wire [3:1] light_E, light_W, light_N, light_S;
  wire ped_light_EW,light_E_R,light_W_R,
  	   ped_light_NS,light_N_R,light_S_R;
  
  traffic_light DUT(clk,reset,E,E_R,pri_E,W,W_R,pri_W,N,N_R,pri_N,S
                   ,S_R,pri_S,light_E,ped_light_EW,light_E_R,light_W
                   ,light_W_R,light_N,ped_light_NS,light_N_R,light_S
                   ,light_S_R);
  
  initial begin
    clk=0;
    forever #5 clk=~clk;
  end
  
  task rst;
    begin
      $display("Reset");
      repeat(1)@(negedge clk);            
      reset = 1;     
      repeat(4)@(posedge clk);
      repeat(1)@(negedge clk); 
      reset = 0;     
      repeat(1)@(posedge clk);  
    end
  endtask
  
  task display;
    begin
      if(DUT.state == 0) begin
        $display("EAST and WEST on");
        $display("light East = %b, ped light = %d, Light West = %b",
                 light_E, ped_light_EW,light_W);
      end
      if(DUT.state == 1) begin
        $display("EAST right on");
        $display("light East = %b, ped light = %d, right turn east = %b",
                 light_E, ped_light_EW,light_E_R);  
      end
      if(DUT.state == 2) begin
        $display("WEST and EAST on");
        $display("light East = %b, ped light = %d, Light West = %b",
                 light_E, ped_light_EW,light_W);
      end
      if(DUT.state == 3) begin
        $display("WEST right on");
        $display("light WEST = %b, ped light = %d, right turn West = %b",
                 light_W, ped_light_EW,light_W_R);  
      end
      if(DUT.state == 4) begin
        $display("NORTH and SOUTH on");
        $display("light NORTH = %b, ped light = %d, Light South = %b",
                 light_N, ped_light_NS,light_S);
      end
      if(DUT.state == 5) begin
        $display("NORTH right on");
        $display("light north = %b, ped light = %d, right turn North = %b",
                 light_N, ped_light_NS,light_N_R);  
      end
      if(DUT.state == 6) begin
        $display("SOUTH and NORTH on");
        $display("light South = %b, ped light = %d, Light North = %b",
                 light_S, ped_light_NS,light_N);
      end
      if(DUT.state == 7) begin
        $display("SOUTH right on");
        $display("light South = %b, ped light = %d,right turn South = %b",
                 light_S, ped_light_NS,light_S_R);  
      end
    end
  endtask
  
  task regular_run;
    begin
      repeat(3)
        $display(" ");
      $display("Regular timed Run");
      rst();
      wait(DUT.state==0);
      display();
      wait(DUT.state==6);
      display();
      wait(DUT.state==2);
      display();
      wait(DUT.state==4);
      display();
      wait(DUT.state==0);
      display();
    end
  endtask
        
  
  task run_with_right;
    begin
      repeat(3)
        $display(" ");
      $display("Run with Right sensors ");
      rst();
      wait(DUT.state==0);
      @(negedge clk);
      E_R = 1;
      display();
      wait(DUT.state==1);
      E_R=0;
      display();
      wait(DUT.state==6)
      @(negedge clk);
      S_R=1;
      display();
      wait(DUT.state==7);
      S_R=0;
      display();
      wait(DUT.state==2)
      @(negedge clk);
      W_R=1;
      display();
      wait(DUT.state==3);
      W_R=0;
      display();
      wait(DUT.state==4)
      @(negedge clk);
      N_R=1;
      display();
      wait(DUT.state==5);
      N_R=0;
      display();
      wait(DUT.state==0);
      display();
    end
  endtask
  
  
  task pri_on;
    input [1:0] D;
    begin
      @(negedge clk);
      if(D==0)
        pri_E=1'b1;
      else if(D==1)
        pri_W=1'b1;
      else if(D==2)
        pri_S=1'b1;
      else if(D==3)
        pri_N=1'b1;
      @(posedge clk);
    end
  endtask
  
  task pri_off;
    input [1:0] D;
    begin
      @(negedge clk);
      if(D==0)
        pri_E=1'b0;
      else if(D==1)
        pri_W=1'b0;
      else if(D==2)
        pri_S=1'b0;
      else if(D==3)
        pri_N=1'b0;
      @(posedge clk);
    end
  endtask
  
  task pri_run;
    begin
      rst();
      repeat(3)
        $display(" ");
      $display("Priority green for South ");
      pri_on(2);
      
      wait(DUT.state==0);
      display();
      @(posedge clk);
      pri_off(2);
      wait(DUT.state==7);
      display();
    end
  endtask
      
        
  
  initial begin
    E = 0; E_R = 0; pri_E = 0;
    W = 0; W_R = 0; pri_W = 0;
    N = 0; N_R = 0; pri_N = 0;
    S = 0; S_R = 0; pri_S = 0;
    $dumpfile("image.vcd");
    $dumpvars(0,tb_traffic_light.DUT);
    //$monitor("state = %d", DUT.state);
    
    regular_run();
    run_with_right();
    pri_run();
    $finish();
  end
endmodule

13_Final_Practice_Projects/118_Traffic_Controller_System/image.vcd
$date
	Thu Jul 16 03:42:00 2026
$end
$version
	Icarus Verilog
$end
$timescale
	1s
$end
$scope module tb_traffic_light $end
$scope module DUT $end
$var wire 1 ! E $end
$var wire 1 " E_R $end
$var wire 1 # N $end
$var wire 1 $ N_R $end
$var wire 1 % S $end
$var wire 1 & S_R $end
$var wire 1 ' W $end
$var wire 1 ( W_R $end
$var wire 1 ) clk $end
$var wire 1 * pri_E $end
$var wire 1 + pri_N $end
$var wire 1 , pri_S $end
$var wire 1 - pri_W $end
$var wire 1 . reset $end
$var parameter 32 / EAST $end
$var parameter 32 0 EAST_R $end
$var parameter 32 1 NORTH $end
$var parameter 32 2 NORTH_R $end
$var parameter 32 3 SOUTH $end
$var parameter 32 4 SOUTH_R $end
$var parameter 32 5 WEST $end
$var parameter 32 6 WEST_R $end
$var reg 4 7 count [3:0] $end
$var reg 3 8 light_E [3:1] $end
$var reg 1 9 light_E_R $end
$var reg 3 : light_N [3:1] $end
$var reg 1 ; light_N_R $end
$var reg 3 < light_S [3:1] $end
$var reg 1 = light_S_R $end
$var reg 3 > light_W [3:1] $end
$var reg 1 ? light_W_R $end
$var reg 3 @ nxt_state [2:0] $end
$var reg 1 A ped_light_EW $end
$var reg 1 B ped_light_NS $end
$var reg 1 C pri $end
$var reg 1 D r $end
$var reg 3 E state [2:0] $end
$upscope $end
$upscope $end
$enddefinitions $end
$comment Show the parameter values. $end
$dumpall
b11 6
b10 5
b111 4
b110 3
b101 2
b100 1
b1 0
b0 /
$end
#0
$dumpvars
bx E
0D
0C
xB
xA
bx @
x?
bx >
x=
bx <
x;
bx :
x9
bx 8
bx 7
x.
0-
0,
0+
0*
0)
0(
0'
0&
0%
0$
0#
0"
0!
$end
#5
1)
#10
1.
0)
#15
1A
b100 <
b100 :
b1 >
b1 8
b0 @
b0 7
b0 E
1)
#20
0)
#25
1)
#30
0)
#35
1)
#40
0)
#45
1)
#50
0.
0)
#55
b1 7
1)
#60
0)
#65
b10 7
1)
#70
0)
#75
b11 7
1)
#80
0)
#85
b100 7
1)
#90
0)
#95
b101 7
1)
#100
0)
#105
b110 7
1)
#110
0)
#115
b111 7
1)
#120
0)
#125
b1000 7
1)
#130
0)
#135
b1001 7
1)
#140
0)
#145
b1010 7
1)
#150
0)
#155
b1011 7
1)
#160
0)
#165
b1100 7
1)
#170
0)
#175
b1101 7
1)
#180
0)
#185
b1110 7
1)
#190
0)
#195
b110 @
b1111 7
1)
#200
0)
#205
1B
b1 :
b1 <
0A
b100 >
b100 8
b110 E
b0 7
1)
#210
0)
#215
b1 7
1)
#220
0)
#225
b10 7
1)
#230
0)
#235
b11 7
1)
#240
0)
#245
b100 7
1)
#250
0)
#255
b101 7
1)
#260
0)
#265
b110 7
1)
#270
0)
#275
b111 7
1)
#280
0)
#285
b1000 7
1)
#290
0)
#295
b1001 7
1)
#300
0)
#305
b1010 7
1)
#310
0)
#315
b1011 7
1)
#320
0)
#325
b1100 7
1)
#330
0)
#335
b1101 7
1)
#340
0)
#345
b1110 7
1)
#350
0)
#355
b10 @
b1111 7
1)
#360
0)
#365
1A
b1 8
b1 >
b100 <
b100 :
b10 E
b0 7
1)
#370
0)
#375
b1 7
1)
#380
0)
#385
b10 7
1)
#390
0)
#395
b11 7
1)
#400
0)
#405
b100 7
1)
#410
0)
#415
b101 7
1)
#420
0)
#425
b110 7
1)
#430
0)
#435
b111 7
1)
#440
0)
#445
b1000 7
1)
#450
0)
#455
b1001 7
1)
#460
0)
#465
b1010 7
1)
#470
0)
#475
b1011 7
1)
#480
0)
#485
b1100 7
1)
#490
0)
#495
b1101 7
1)
#500
0)
#505
b1110 7
1)
#510
0)
#515
b100 @
b1111 7
1)
#520
0)
#525
0A
b100 >
b100 8
b100 E
b0 7
1)
#530
0)
#535
b1 7
1)
#540
0)
#545
b10 7
1)
#550
0)
#555
b11 7
1)
#560
0)
#565
b100 7
1)
#570
0)
#575
b101 7
1)
#580
0)
#585
b110 7
1)
#590
0)
#595
b111 7
1)
#600
0)
#605
b1000 7
1)
#610
0)
#615
b1001 7
1)
#620
0)
#625
b1010 7
1)
#630
0)
#635
b1011 7
1)
#640
0)
#645
b1100 7
1)
#650
0)
#655
b1101 7
1)
#660
0)
#665
b1110 7
1)
#670
0)
#675
b0 @
b1111 7
1)
#680
0)
#685
1A
b1 >
b1 8
b0 E
b0 7
1)
#690
1.
0)
#695
1)
#700
0)
#705
1)
#710
0)
#715
1)
#720
0)
#725
1)
#730
0.
0)
#735
b1 7
1)
#740
1"
0)
#745
b10 7
1)
#750
0)
#755
b11 7
1)
#760
0)
#765
b100 7
1)
#770
0)
#775
b1 @
b101 7
1)
#780
0)
#785
19
0A
b100 >
b1 8
0"
b1 E
b110 7
1)
#790
0)
#795
b111 7
1)
#800
0)
#805
b1000 7
1)
#810
0)
#815
b1001 7
1)
#820
0)
#825
b1010 7
1)
#830
0)
#835
b1011 7
1)
#840
0)
#845
b1100 7
1)
#850
0)
#855
b1101 7
1)
#860
0)
#865
b1110 7
1)
#870
0)
#875
b110 @
b1111 7
1)
#880
0)
#885
b1 :
b1 <
b100 8
b110 E
b0 7
1)
#890
1&
0)
#895
b1 7
1)
#900
0)
#905
b10 7
1)
#910
0)
#915
b11 7
1)
#920
0)
#925
b100 7
1)
#930
0)
#935
b101 7
1)
#940
0)
#945
b110 7
1)
#950
0)
#955
b111 @
b111 7
1)
#960
0)
#965
1=
b1 <
b100 :
0&
b111 E
b1000 7
1)
#970
0)
#975
b1001 7
1)
#980
0)
#985
b1010 7
1)
#990
0)
#995
b1011 7
1)
#1000
0)
#1005
b1100 7
1)
#1010
0)
#1015
b1101 7
1)
#1020
0)
#1025
b1110 7
1)
#1030
0)
#1035
b10 @
b1111 7
1)
#1040
0)
#1045
1A
b1 8
b1 >
b100 <
b10 E
b0 7
1)
#1050
1(
0)
#1055
b1 7
1)
#1060
0)
#1065
b10 7
1)
#1070
0)
#1075
b11 7
1)
#1080
0)
#1085
b100 7
1)
#1090
0)
#1095
b1 @
b101 7
1)
#1100
0)
#1105
0A
b100 >
b1 8
b11 @
b1 E
b110 7
1)
#1110
0)
#1115
0(
1?
b1 >
b100 8
b111 7
b11 E
1)
#1120
0)
#1125
b1000 7
1)
#1130
0)
#1135
b1001 7
1)
#1140
0)
#1145
b1010 7
1)
#1150
0)
#1155
b1011 7
1)
#1160
0)
#1165
b1100 7
1)
#1170
0)
#1175
b1101 7
1)
#1180
0)
#1185
b1110 7
1)
#1190
0)
#1195
b100 @
b1111 7
1)
#1200
0)
#1205
b100 >
b100 E
b0 7
1)
#1210
1$
0)
#1215
b1 7
1)
#1220
0)
#1225
b10 7
1)
#1230
0)
#1235
b11 7
1)
#1240
0)
#1245
b100 7
1)
#1250
0)
#1255
b1 @
b101 7
1)
#1260
0)
#1265
b1 8
b101 @
b1 E
b110 7
1)
#1270
0)
#1275
0$
1;
b1 :
b100 8
b111 7
b101 E
1)
#1280
0)
#1285
b1000 7
1)
#1290
0)
#1295
b1001 7
1)
#1300
0)
#1305
b1010 7
1)
#1310
0)
#1315
b1011 7
1)
#1320
0)
#1325
b1100 7
1)
#1330
0)
#1335
b1101 7
1)
#1340
0)
#1345
b1110 7
1)
#1350
0)
#1355
b0 @
b1111 7
1)
#1360
0)
#1365
1A
b1 >
b1 8
b100 :
b0 E
b0 7
1)
#1370
1.
0)
#1375
1)
#1380
0)
#1385
1)
#1390
0)
#1395
1)
#1400
0)
#1405
1)
#1410
0.
0)
#1415
b1 7
1)
#1420
b111 @
1D
1,
0)
#1425
b1 <
0A
b100 >
b100 8
0D
b111 E
b0 7
1)
#1430
0)
#1435
b1 7
1)
#1440
0,
0)
#1445
b10 7
1)
