07_Counters/design.v
module up_counter(input clk,
                  input rst,
                  output reg [3:0]count);
  
  always@(posedge clk or posedge rst)
    begin
      if(rst)
        count <= 4'd0;
      else
        count <= count + 1;
    end
  
endmodule

07_Counters/058_Up_Counter/design_tb.v
module up_counter_tb();
  reg clk,rst;
  wire [3:0] count;
  
  up_counter DUT(.clk(clk),
                 .rst(rst),
                 .count(count)
                );
  
  always begin
    #1 clk = ~clk;
  end
  
  initial begin
    $dumpfile("image.vcd");
    $dumpvars(0,up_counter_tb);
  end
  
  initial begin
    clk = 0;
    rst = 1;
    $monitor("count = %b",count);
    #5 rst = 0;
    @(negedge clk);
    @(negedge clk);
    @(negedge clk);
    repeat(20)@(negedge clk);
    $finish();
  end
endmodule

07_Counters/058_Up_Counter/image.vcd
$date
	Fri Jun  5 05:05:15 2026
$end
$version
	Icarus Verilog
$end
$timescale
	1s
$end
$scope module up_counter_tb $end
$var wire 4 ! count [3:0] $end
$var reg 1 " clk $end
$var reg 1 # rst $end
$scope module DUT $end
$var wire 1 " clk $end
$var wire 1 # rst $end
$var reg 4 $ count [3:0] $end
$upscope $end
$upscope $end
$enddefinitions $end
$comment Show the parameter values. $end
$dumpall
$end
#0
$dumpvars
b0 $
1#
0"
b0 !
$end
#1
1"
#2
0"
#3
1"
#4
0"
#5
b1 !
b1 $
1"
0#
#6
0"
#7
b10 !
b10 $
1"
#8
0"
#9
b11 !
b11 $
1"
#10
0"
#11
b100 !
b100 $
1"
#12
0"
#13
b101 !
b101 $
1"
#14
0"
#15
b110 !
b110 $
1"
#16
0"
#17
b111 !
b111 $
1"
#18
0"
#19
b1000 !
b1000 $
1"
#20
0"
#21
b1001 !
b1001 $
1"
#22
0"
#23
b1010 !
b1010 $
1"
#24
0"
#25
b1011 !
b1011 $
1"
#26
0"
#27
b1100 !
b1100 $
1"
#28
0"
#29
b1101 !
b1101 $
1"
#30
0"
#31
b1110 !
b1110 $
1"
#32
0"
#33
b1111 !
b1111 $
1"
#34
0"
#35
b0 !
b0 $
1"
#36
0"
#37
b1 !
b1 $
1"
#38
0"
#39
b10 !
b10 $
1"
#40
0"
#41
b11 !
b11 $
1"
#42
0"
#43
b100 !
b100 $
1"
#44
0"
#45
b101 !
b101 $
1"
#46
0"
#47
b110 !
b110 $
1"
#48
0"
#49
b111 !
b111 $
1"
