02_Basic_Combinational/017_3to8_Decoder/design.v
module decoder_3x8(input a,
                   input b,
                   input c,
                   input e,
                   output reg [7:0] y);
  
  always@(*) begin
    if(!e)
      y = 0;
    else
      case({a,b,c})
        3'b000: y = 8'd1;
        3'b001: y = 8'd2;
        3'b010: y = 8'd4;
        3'b011: y = 8'd8;
        3'b100: y = 8'd16;
        3'b101: y = 8'd32;
        3'b110: y = 8'd64;
        3'b111: y = 8'd128;
        default y = 8'd0;
      endcase
  end
endmodule

02_Basic_Combinational/017_3to8_Decoder/design_tb.v
module decoder_3x8_tb();
  reg a,b,c,e;
  wire [7:0]y;
  
  decoder_3x8 DUT(.a(a),
                  .b(b),
                  .c(c),
                  .e(e),
                  .y(y));
  
  initial begin
    $dumpfile("image.vcd");
    $dumpvars(0);
    e = 0;
    $monitor("e = %b, a = %b, b = %b, c = %b, y = %b",e,a,b,c,y);
    #10 e = 1; a = 0; b = 0; c = 0;
    #10 e = 1; a = 0; b = 0; c = 1;
    #10 e = 1; a = 0; b = 1; c = 0;
    #10 e = 1; a = 0; b = 1; c = 1;
    #10 e = 1; a = 1; b = 0; c = 0;
    #10 e = 1; a = 1; b = 0; c = 1;
    #10 e = 1; a = 1; b = 1; c = 0;
    #10 e = 1; a = 1; b = 1; c = 1;
    #10 $finish();
  end
endmodule

02_Basic_Combinational/017_3to8_Decoder/image.vcd
$date
	Thu Jun  4 05:43:42 2026
$end
$version
	Icarus Verilog
$end
$timescale
	1s
$end
$scope module decoder_3x8_tb $end
$var wire 8 ! y [7:0] $end
$var reg 1 " a $end
$var reg 1 # b $end
$var reg 1 $ c $end
$var reg 1 % e $end
$scope module DUT $end
$var wire 1 " a $end
$var wire 1 # b $end
$var wire 1 $ c $end
$var wire 1 % e $end
$var reg 8 & y [7:0] $end
$upscope $end
$upscope $end
$enddefinitions $end
$comment Show the parameter values. $end
$dumpall
$end
#0
$dumpvars
b0 &
0%
x$
x#
x"
b0 !
$end
#10
b1 !
b1 &
0$
0#
0"
1%
#20
b10 !
b10 &
1$
#30
b100 !
b100 &
0$
1#
#40
b1000 !
b1000 &
1$
#50
b10000 !
b10000 &
0$
0#
1"
#60
b100000 !
b100000 &
1$
#70
b1000000 !
b1000000 &
0$
1#
#80
b10000000 !
b10000000 &
1$
