02_Basic_Combinational/8x1MUX/design.v
module mux_4(input [3:0] i,
             input [1:0] s,
             input en,
             output reg y);
  
  always@(*) begin
    if(en)
      case(s)
        2'b00: y = i[0];
        2'b01: y = i[1];
        2'b10: y = i[2];
        2'b11: y = i[3];
        default: y = 0 ;
      endcase
    else y = 0;
  end
  
endmodule

module mux_8(input [7:0] i,
             input [2:0] s,
             output y);
  
  wire mux1,mux2;
  wire s2;
  
  not(s2,s[2]);
  
  mux_4 mux_1(.i(i[3:0]),
              .s(s[1:0]),
              .en(s2),
              .y(mux1));
  
  mux_4 mux_2(.i(i[7:4]),
              .s(s[1:0]),
              .en(s[2]),
              .y(mux2));
   
  or(y,mux1,mux2);
  
endmodule

02_Basic_Combinational/8x1MUX/design_tb.v
module mux_8_tb();
  reg [7:0] i;
  reg [2:0] s;
  wire y;
  
  mux_8 DUT(.i(i),
            .s(s),
            .y(y)
           );
  
  initial begin
    i=1;
    s=3'd0;
    $dumpfile("image.vcd");
    $dumpvars(0);
    $monitor("s = %b, i = %b, y = %b",s,i,y);
    
    #10 s = 3'd1; i = 8'd2;
    #10 s = 3'd2; i = 8'd4;
    #10 s = 3'd3; i = 8'd8;
    #10 s = 3'd4; i = 8'd16;
    #10 s = 3'd5; i = 8'd32;
    #10 s = 3'd6; i = 8'd64;
    #10 s = 3'd7; i = 8'd128;
    #10 $finish();
  end
endmodule
    

// module mux_4_tb();
//   reg [3:0] i;
//   reg [1:0] s;
//   wire y;
  
//   mux_4 DUT(.i(i),
//             .s(s),
//             .y(y)
//            );
  
//   initial begin
//     i=1;
//     s='0;
//     $dumpfile("image.vcd");
//     $dumpvars(0);
//     $monitor("s = %b, i = %b, y = %b",s,i,y);
    
//     #10 s = 2'd1; i = 4'd2;
//     #10 s = 2'd2; i = 4'd4;
//     #10 s = 2'd3; i = 4'd8;
//     #10 $finish();
//   end
// endmodule

02_Basic_Combinational/8x1MUX/image.vcd
$date
	Thu Jun  4 01:33:59 2026
$end
$version
	Icarus Verilog
$end
$timescale
	1s
$end
$scope module mux_8_tb $end
$var wire 1 ! y $end
$var reg 8 " i [7:0] $end
$var reg 3 # s [2:0] $end
$scope module DUT $end
$var wire 8 $ i [7:0] $end
$var wire 3 % s [2:0] $end
$var wire 1 & s2 $end
$var wire 1 ! y $end
$var wire 1 ' mux2 $end
$var wire 1 ( mux1 $end
$scope module mux_1 $end
$var wire 1 & en $end
$var wire 4 ) i [3:0] $end
$var wire 2 * s [1:0] $end
$var reg 1 ( y $end
$upscope $end
$scope module mux_2 $end
$var wire 1 + en $end
$var wire 4 , i [3:0] $end
$var wire 2 - s [1:0] $end
$var reg 1 ' y $end
$upscope $end
$upscope $end
$upscope $end
$enddefinitions $end
$comment Show the parameter values. $end
$dumpall
$end
#0
$dumpvars
b0 -
b0 ,
0+
b0 *
b1 )
1(
0'
1&
b0 %
b1 $
b0 #
b1 "
1!
$end
#10
b10 )
b1 *
b1 -
b10 "
b10 $
b1 #
b1 %
#20
b100 )
b10 *
b10 -
b100 "
b100 $
b10 #
b10 %
#30
b1000 )
b11 *
b11 -
b1000 "
b1000 $
b11 #
b11 %
#40
0&
0(
1'
b0 )
b1 ,
b0 *
b0 -
1+
b10000 "
b10000 $
b100 #
b100 %
#50
b10 ,
b1 *
b1 -
b100000 "
b100000 $
b101 #
b101 %
#60
b100 ,
b10 *
b10 -
b1000000 "
b1000000 $
b110 #
b110 %
#70
b1000 ,
b11 *
b11 -
b10000000 "
b10000000 $
b111 #
b111 %
